MANIFEST.in
README.md
setup.cfg
setup.py
entangled/__init__.py
entangled/annotate.py
entangled/bootstrap.py
entangled/config.py
entangled/doctest.py
entangled/doctest_main.py
entangled/inject.py
entangled/tangle.py
entangled/typing.py
entangled/pymd/__init__.py
entangled/schema/Card.dhall
entangled_filters.egg-info/PKG-INFO
entangled_filters.egg-info/SOURCES.txt
entangled_filters.egg-info/dependency_links.txt
entangled_filters.egg-info/entry_points.txt
entangled_filters.egg-info/requires.txt
entangled_filters.egg-info/top_level.txt