Metadata-Version: 2.1
Name: entangled-filters
Version: 0.8.3
Summary: Set of Pandoc filters to aid in literate programming
Home-page: https://entangled.github.io/
Author: Johan Hidding
Author-email: j.hidding@esciencecenter.nl
License: UNKNOWN
Project-URL: Bug Tracker, https://github.com/entangled/filters/issues/
Project-URL: Documentation, https://entangled.github.io/filters/
Project-URL: Source Code, https://github.com/entangled/filters/
Keywords: literate programming
Platform: UNKNOWN
Classifier: License :: OSI Approved :: Apache Software License
Classifier: Development Status :: 3 - Alpha
Classifier: Intended Audience :: Science/Research
Classifier: Intended Audience :: Developers
Classifier: Environment :: Console
Classifier: Natural Language :: English
Classifier: Operating System :: OS Independent
Classifier: Programming Language :: Python :: 3.7
Classifier: Programming Language :: Python :: 3.8
Classifier: Topic :: Education
Classifier: Topic :: Documentation
Classifier: Topic :: Scientific/Engineering
Classifier: Topic :: Software Development
Classifier: Topic :: Software Development :: Documentation
Classifier: Topic :: Software Development :: Testing
Classifier: Topic :: Text Processing :: Markup
Provides-Extra: test
